multicontents/__init__.py
multicontents/multi_versions_file_checkpoints.py
multicontents/multicontents_manager.py
tests/__init__.py
tests/integration_test.py
tests/multi_versions_file_checkpoints_test.py
tests/multicontents_manager_test.py
multicontents-0.4.0.dist-info/LICENSE.txt
multicontents-0.4.0.dist-info/METADATA
multicontents-0.4.0.dist-info/WHEEL
multicontents-0.4.0.dist-info/top_level.txt
multicontents-0.4.0.dist-info/RECORD
