Metadata-Version: 2.1
Name: multicontents
Version: 0.4.0
Summary: providing contents from multiple sources in jupyter notebook
Home-page: https://github.com/lydian/multicontents
Author: Lydian Lee
Author-email: lydianly@gmail.com
Maintainer: Lydian Lee
Maintainer-email: lydianly@gmail.com
License: UNKNOWN
Platform: UNKNOWN
Classifier: Development Status :: 4 - Beta
Classifier: Environment :: Web Environment
Classifier: Intended Audience :: Developers
Classifier: Natural Language :: English
Classifier: Operating System :: OS Independent
Classifier: Programming Language :: Python
Requires-Python: >=3.6
Requires-Dist: notebook
Requires-Dist: ipykernel
